odoo9_addon_partner_stock_risk-9.0.1.0.0-py2.7-nspkg.pth
odoo9_addon_partner_stock_risk-9.0.1.0.0.dist-info/DESCRIPTION.rst
odoo9_addon_partner_stock_risk-9.0.1.0.0.dist-info/METADATA
odoo9_addon_partner_stock_risk-9.0.1.0.0.dist-info/RECORD
odoo9_addon_partner_stock_risk-9.0.1.0.0.dist-info/WHEEL
odoo9_addon_partner_stock_risk-9.0.1.0.0.dist-info/metadata.json
odoo9_addon_partner_stock_risk-9.0.1.0.0.dist-info/namespace_packages.txt
odoo9_addon_partner_stock_risk-9.0.1.0.0.dist-info/top_level.txt
odoo_addons/partner_stock_risk/README.rst
odoo_addons/partner_stock_risk/__init__.py
odoo_addons/partner_stock_risk/__openerp__.py
odoo_addons/partner_stock_risk/i18n/es.po
odoo_addons/partner_stock_risk/models/__init__.py
odoo_addons/partner_stock_risk/models/stock.py
odoo_addons/partner_stock_risk/tests/__init__.py
odoo_addons/partner_stock_risk/tests/test_partner_stock_risk.py
